minimalcluster/__init__.py
minimalcluster/master_node.py
minimalcluster/worker_node.py
minimalcluster-0.1.0.dev13.dist-info/DESCRIPTION.rst
minimalcluster-0.1.0.dev13.dist-info/METADATA
minimalcluster-0.1.0.dev13.dist-info/RECORD
minimalcluster-0.1.0.dev13.dist-info/WHEEL
minimalcluster-0.1.0.dev13.dist-info/metadata.json
minimalcluster-0.1.0.dev13.dist-info/top_level.txt
