Metadata-Version: 2.0
Name: minimalcluster
Version: 0.1.0.dev13
Summary: A minimal cluster computing framework
Home-page: https://github.com/XD-DENG/minimalcluster-py
Author: Xiaodong DENG
Author-email: xd.deng.r@gmail.com
License: MIT
Keywords: parallel cluster multiprocessing
Platform: UNKNOWN
